{"queryCode":{"vto":"Товар не входит в перечень изъятий ВТО","rate":{"grName":"66 (2022) Решение Коллегии ЕЭК от 19.04.2022","url":"https://docs.eaeunion.org/docs/ru-ru/01532480/err_28042022_66","rateStr":"10%"},"transition":[]},"similar":["крупа пассии фасоль","фасоль белая горис крупа","фасоль сушеная","фасоль красная горис крупа","фасоль красеая горис крупа","фасоль белая крупа","крупа цесна фасоль белая"],"keyWords":null,"resultWithDescription":[{"probability":100,"code":"0713339000","description":"Фасоль обыкновенная, включая белую мелкосеменную фасоль (phaseolus  vulgaris), прочих целей, но не для посева","startDate":"2022-01-01T00:00:00","endDate":null,"isOld":false}],"result":null,"group":{"code":"0713XXXXXX","name":"Овощи бобовые сушеные, лущеные, очищенные от семенной кожуры или неочищенные, колотые или неколотые:"},"session":{"id":"be896490-d2c4-4cc2-b7f0-f15fa7bad661","date":"2023-07-25T16:00:07.1089641Z","remain":null},"codesCount":1,"operationTimeSpan":"00:00:00.1177786","identical":false,"responseState":201,"errorMessage":null,"success":true}