{"queryCode":{"vto":"Товар не входит в перечень изъятий ВТО","rate":{"grName":"80 Решение Совета ЕЭК от 14.09.2021","url":"https://docs.eaeunion.org/docs/ru-ru/01530209/err_06102021_80","rateStr":"5%"},"transition":[]},"similar":["железо","железа","пигмент для бетона","железа поджелудочная","alumine oxide","bayferrox","железо кровельное","прутковое железо","пигменты для бетона","желез","trioctylphosphine oxide"],"keyWords":null,"resultWithDescription":[{"probability":100,"code":"2821100000","description":"Оксиды и гидроксиды железа","startDate":"2022-01-01T00:00:00","endDate":null,"isOld":false}],"result":null,"group":{"code":"2821XXXXXX","name":"Оксиды и гидроксиды железа; красители минеральные, содержащие 70\u00A0мас.% или более химически связанного железа в пересчете на Fе2O3:"},"session":{"id":"44d3577a-394a-4f6c-94ef-d686097b7319","date":"2023-07-25T15:11:00.8697469Z","remain":null},"codesCount":1,"operationTimeSpan":"00:00:00.0460779","identical":false,"responseState":201,"errorMessage":null,"success":true}