{"queryCode":{"vto":"Товар не входит в перечень изъятий ВТО","rate":{"grName":"150 Решение Совета ЕЭК от 23.09.2022","url":"https://docs.eaeunion.org/docs/ru-ru/01536385/err_26092022_150","rateStr":"5%"},"transition":[]},"similar":["пластырь","лейкопластырь","ткан","перцовый пластырь","пластыри","пластырь кордовый","пластырь медицинский","лейкопластыри","бактерицид","нимпласт","согревающий пластырь","балончик перцовый","мозольный пластырь","пластыри медицинские","повязка медицинская","адгезивная повязка для раны стерильная","elastic","лейкопластырь медицинский","лейкопластырь санипласт","пластырь от боли","бактерицидный","адгезивная повязка полиуретановая стерильная","вольтарен пластырь трансдермальный сут","гемостат пластырь","mepiform повязка самоклеящаяся","кинезио","дыши","бактерицидная медицинская повязка","антисептик медицинский","extraplast beauty пластырь","cath fix","неткан","перцовый перфорирован пластырь","перцовый пластырь перфорации","пластыри от комаров","пластырь радильный","пластырь разогревающий","повязка для ран","рад пластырь","hartmann cosmos пластырь","steri strip","silkofix повязка на нетканной основе","hartmann бранолинд повязка мазевая","бактерицидные","лейкоп мультипласт набор фиксир","лейкопласт veroplast","лейкопл","лейкопласт veroplast бактерицид","лейкопластырь tianhe zhuifeng gao","лейкопластырь бактер"],"keyWords":null,"resultWithDescription":[{"probability":100,"code":"3005100000","description":"Материал перевязочный адгезивный и прочие изделия, имеющие липкий слой","startDate":"2022-01-01T00:00:00","endDate":null,"isOld":false}],"result":null,"group":{"code":"3005XXXXXX","name":"Вата, марля, бинты и аналогичные изделия (например, перевязочный материал, лейкопластыри, припарки), пропитанные или покрытые фармацевтическими веществами или расфасованные в формы или упаковки для розничной продажи, предназначенные для использования в медицине, хирургии, стоматологии или ветеринарии:"},"session":{"id":"a4ad41c5-19fa-42e2-a0eb-405d40d72d34","date":"2023-07-25T12:19:40.0097524Z","remain":null},"codesCount":1,"operationTimeSpan":"00:00:00.0593472","identical":false,"responseState":201,"errorMessage":null,"success":true}