{"queryCode":{"vto":"Товар не входит в перечень изъятий ВТО","rate":{"grName":"135 Решение Коллегии ЕЭК от 28.09.2022","url":"https://docs.eaeunion.org/docs/ru-ru/01536442/err_30092022_135","rateStr":"5%"},"transition":[]},"similar":["эфирное масло","пихтовое масло","эфирное пихтовое масло","эфирное кедровое масло","эвкалиптовое масло","эвкалиптовое масло шаровидное","эфирное масло можжевельника","эфирное масло корицы","эвкалиптовое масло глобулос","масло эфирное корица","антена эфирная","эвкалипта эфирное масло клео аромамарка","дезинфицирующ","сырье чайное","эфирное масло кедра","эфирное масло герани","гейпфрут масло эфирное леос","масло эвкалипт миролла","масло пихтовое эфирное миролла","ароматика масло эфирное лимон","масло вербеновое","масло аниса","кубеба","кедра атласского","кедр атласский масло","живица кедра","ароматика масло эфирное гвоздика","ароматика масло чайного дерева","ароматика масло жожоба","масло пачули","охо oel ифыа","эфирное масло пихты","хвой","бессмертник"],"keyWords":null,"resultWithDescription":[{"probability":100,"code":"3301294100","description":"Прочие эфирные масла, кроме эфирных масел цитрусовых плодов, содержащие терпены","startDate":"2022-01-01T00:00:00","endDate":null,"isOld":false}],"result":null,"group":{"code":"3301XXXXXX","name":"Масла эфирные (содержащие или не содержащие терпены), включая конкреты и абсолюты; резиноиды; экстрагированные эфирные масла; концентраты эфирных масел в жирах, нелетучих маслах, восках или аналогичных продуктах, получаемые методом анфлеража или мацерацией; терпеновые побочные продукты детерпенизации эфирных масел; водные дистилляты и водные растворы эфирных масел:"},"session":{"id":"24029eea-7100-45c1-9aea-049caab56649","date":"2023-07-25T14:41:56.561786Z","remain":null},"codesCount":1,"operationTimeSpan":"00:00:00.0380036","identical":false,"responseState":201,"errorMessage":null,"success":true}