{"queryCode":{"vto":"Товар не входит в перечень изъятий ВТО","rate":{"grName":"80 Решение Совета ЕЭК от 14.09.2021","url":"https://docs.eaeunion.org/docs/ru-ru/01530209/err_06102021_80","rateStr":"6.5%"},"transition":[]},"similar":["влажные салфетки","чистящие салфетки hobot цена за в упаковке совместимы с","влажная салфетка","дезинфицирующие салфетки","антибактериальные салфетки","салфетки пропитанные изопропанолом","коробка для салфеток","салфетки для диспенсера","салфетк","чистящие салфетки","влажные антибактериальные салфетки","салфетка перфорированная","салфетка чистящая","хозяйственные","салфетки чистящие влажные","полисорбат","салфетки влаж","салфетки влажные гигиенические","салфетки влажные для оптики","aura amh","салфетки влажные клинекс","салфетки для экранов","хозяйственное","влажные салфетки ola","дисней бэби мыло","влажные салфетка","влажн салф","бумажный салфетка","elkos мыло хозяйственное","aura влажные салфетки","салфетки влажные для ноутбука","салфетки универсал","салфетки хозяйственные","феноксиэтанол","чистящие салфетки для мониторов","влажные салфетки ушастый нянь","helen harper влажные салфетки","аура влажные салфекти антибакт с крыш","влажн салф очищающие","влажные салфетки aura family освежающие в упаковке","аура антибактериальные салфетки ромашка","влажные салфетки luna fresh карманные cities","влажные салфетки для экрана","влажные салфетки детей rio wet towel","baby салфетки","влажные салфетки ola silk sence универсальные","кватерниум","кокамидопропилбетаин","интим","влажный салфетка"],"keyWords":null,"resultWithDescription":[{"probability":100,"code":"3401190000","description":"Прочее мыло; поверхностно-активные органические вещества и средства, в форме брусков, кусков или в виде фигурных изделий; бумага, вата, войлок или фетр и нетканые материалы, пропитан. или покрытые мылом или моющим средством","startDate":"2022-01-01T00:00:00","endDate":null,"isOld":false}],"result":null,"group":{"code":"3401XXXXXX","name":"Мыло; поверхностно-активные органические вещества и средства, применяемые в качестве мыла, в форме брусков, кусков или в виде формованных изделий, содержащие или не содержащие мыло; поверхностно-активные органические вещества и средства для мытья кожи в виде жидкости или крема и расфасованные для розничной продажи, содержащие или не содержащие мыло; бумага, вата, войлок или фетр и нетканые материалы, пропитанные или покрытые мылом или моющим средством:"},"session":{"id":"695d9cb9-0547-45b2-bb26-64c0bcaf82f0","date":"2023-07-25T12:18:24.5794844Z","remain":null},"codesCount":1,"operationTimeSpan":"00:00:00.0453119","identical":false,"responseState":201,"errorMessage":null,"success":true}