{"queryCode":{"vto":"Товар не входит в перечень изъятий ВТО","rate":{"grName":"80 Решение Совета ЕЭК от 14.09.2021","url":"https://docs.eaeunion.org/docs/ru-ru/01530209/err_06102021_80","rateStr":"6.5%"},"transition":[]},"similar":["сургуч","бетонит","emulgade","cutina"],"keyWords":null,"resultWithDescription":[{"probability":100,"code":"3404900001","description":"Воски готовые, включая сургучи","startDate":"2022-01-01T00:00:00","endDate":null,"isOld":false}],"result":null,"group":{"code":"3404XXXXXX","name":"Воски искусственные и готовые воски:"},"session":{"id":"f2ce9cf2-72c7-44ae-94f5-ab7e6d4fd049","date":"2023-07-25T13:53:02.028926Z","remain":null},"codesCount":1,"operationTimeSpan":"00:00:00.0408874","identical":false,"responseState":201,"errorMessage":null,"success":true}