{"queryCode":{"vto":"Товар не входит в перечень изъятий ВТО","rate":{"grName":"80 Решение Совета ЕЭК от 14.09.2021","url":"https://docs.eaeunion.org/docs/ru-ru/01530209/err_06102021_80","rateStr":"5%"},"transition":[]},"similar":["sheets","графлекс"],"keyWords":null,"resultWithDescription":[{"probability":100,"code":"3801900009","description":"Прочие продукты, полученные на основе графита или прочих форм углерода, в виде паст, блоков, пластин или прочих полуфабрикатов","startDate":"2022-01-01T00:00:00","endDate":null,"isOld":false}],"result":null,"group":{"code":"3801XXXXXX","name":"Графит искусственный; графит коллоидный или полуколлоидный; продукты, полученные на основе графита или прочего углерода, в виде паст, блоков, пластин или прочих полуфабрикатов:"},"session":{"id":"3bd46069-cc95-4309-8c8d-0dce2b0adf87","date":"2023-07-25T15:01:45.5348755Z","remain":null},"codesCount":1,"operationTimeSpan":"00:00:00.0635054","identical":false,"responseState":201,"errorMessage":null,"success":true}