{"queryCode":{"vto":"Товар не входит в перечень изъятий ВТО","rate":{"grName":"80 Решение Совета ЕЭК от 14.09.2021","url":"https://docs.eaeunion.org/docs/ru-ru/01530209/err_06102021_80","rateStr":"6.5%"},"transition":[]},"similar":["пленка пвх","пвх","термоусадочная пленка","клеенка пвх","клеенка прозрачная","полуотвод пвх","пленка для вышивки","кромка мебельная пвх","термоусадочная","термоусадочная этикетка","морожное","мебель из пвх","кромка для линолеума","пленки пвх","эви","скатерть пленка","поливинилхлоридная пленка","подложка пвх","пленка светлая","пленка рулонная","пленка для переплета","клеёнка с пвх покрытием","лист пвх дуб сонома","гофратруба пвх","деревянная подложка","пленка из пвх","пвх пористый","пвх клеенка для стола","обложка из пленки","кант пвх","клеенка прозрачная из пвх","белый пвх an","miniature furniture"],"keyWords":null,"resultWithDescription":[{"probability":100,"code":"3920491009","description":"Прочие плиты, листы, пленка и полосы или ленты, прочие, из пластмасс, непористые и неармированные, неслоистые, без подложки и не соединенные аналогичным способом с другими материалами, из полимеров винилхлорида, толщиной не более 1 мм, гибкие","startDate":"2022-01-01T00:00:00","endDate":null,"isOld":false}],"result":null,"group":{"code":"3920XXXXXX","name":"Плиты, листы, пленка и полосы или ленты, прочие, из пластмасс, непористые и неармированные, неслоистые, без подложки и не соединенные аналогичным способом с другими материалами:"},"session":{"id":"401bfdcc-38d4-4d33-9877-a94fe2cffcd9","date":"2023-07-25T12:50:33.7361032Z","remain":null},"codesCount":1,"operationTimeSpan":"00:00:00.0622519","identical":false,"responseState":201,"errorMessage":null,"success":true}