{"queryCode":{"vto":"Товар не входит в перечень изъятий ВТО","rate":{"grName":"80 Решение Совета ЕЭК от 14.09.2021","url":"https://docs.eaeunion.org/docs/ru-ru/01530209/err_06102021_80","rateStr":"1.75 ЕВРО за КГ"},"transition":[]},"similar":["свитшот","кофта мужская","свитшот мужской","жилет сигнальный оранжевый","сигнальный жилет лимонный","флажок сигнальный","кофты мужские","кофта с замком","свитшот хлопок эластан","свитер носки футболка","толстовка из флиса","шерсть альпаки","кофта из химических нитей для мальчика","мужская джерси","мужская олимпийка","мужская шерстяная кофта","кардиган мужской из смесовый пряжи","толстовка renault","свитер тренировочный","мужская кофта синтетика","hoody","кофта флисовая для мальчика","кофта флисовая для мальчков","жилеты мужские из химических нитей машинного вязания","жилет сигнальный с соп оранжевый","жилет сигнальный светоотражающий","альпаки","джерси мужской","жакет мальчик шерсть","пуловер из флиса","свитер мужской из флисовой ткани","свитшот трикотажный","сигнальный флажок красный","толстов","толстовка для занятия велоспортом хлопок полиэстер","подвяз трикотажный полиэстер арт tby черный с белыми и красной полосами","мужской свитер abercrombie and fitch хлопок","мужской свитер красный polo assn хлопок полиэстер флис","жилет сигнальный мужской","pullover","жилет сигнальный полиэфир лимонный","жилетка для персонала","жилеты сигнальные зеленые","кофта мужская на молнии","кофта мужская овечья шерсть","кофта мужская ткань синтетика","кофта мужская трикотаж синтетика","кофта из флиса","мужская кофта флисовая полиэстер","жилет сигнальный оранж"],"keyWords":null,"resultWithDescription":[{"probability":100,"code":"6110309100","description":"Прочие свитера, пуловеры, джемперы, жилеты и аналогичные изделия трикотажные, из химических нитей, для мужчин или мальчиков, машинного или ручного вязания","startDate":"2022-01-01T00:00:00","endDate":null,"isOld":false}],"result":null,"group":{"code":"6110XXXXXX","name":"Свитеры, пуловеры, кардиганы, жилеты и аналогичные изделия трикотажные машинного или ручного вязания:"},"session":{"id":"317ca1cf-6cc8-4925-9599-9659d78c1a40","date":"2023-07-25T13:22:18.3922558Z","remain":null},"codesCount":1,"operationTimeSpan":"00:00:00.0359292","identical":false,"responseState":201,"errorMessage":null,"success":true}