{"queryCode":{"vto":"Товар не входит в перечень изъятий ВТО","rate":{"grName":"80 Решение Совета ЕЭК от 14.09.2021","url":"https://docs.eaeunion.org/docs/ru-ru/01530209/err_06102021_80","rateStr":"12%"},"transition":[]},"similar":["перчатки прорезиненные","перчатки тканевые","перчатки маслобензостойкие","перчатки облитые латексом универсальные","перчатк","белые перчатки с резиновой ладонью для официантов","вязаная","перчатки с резиновым покрытием","перчатки эластичные","перчатки с нитриловым покрытием","перчатки защитные маслобензостойкие","перчатки для хозяйственных нужд тканевые","антивибрационные перчатки","авоська вязаная","вязаная миниатюра","перчатки для защиты рук нитриловые маслобензостойкие на трикотажной основе","перчатки обливные","перчатки нитриловое покрытие","перчатки облитые латексом","перчатки нитриловые полный облив крага аналог hycron","перчатки с латексом","перчатки с латексным покрытием облив","перчатки рабочие с резиновым покрытием","перчатки сшитые","перчатки садовые с когтями","перчатки с рельефным латексным","перчатки с полным или неполным покрытием","перчатки с одинарным латексным покрытием","перчатки с обливом","перчатки рабочие с нитриловым покрытием материал хлопчатобумажный","перчатки рабочие прорезиненные","перчатки прорезиненные оранж","перчатки прор","перчатки полиэфирные нитрильный облив","перчатки зелен облив супер","перчатки защитные с покрытием резиной трикотажные","перчатки облитые зеленый","перчатки облитые","перчатки нити с пхв","перчатки маслобензостойкие красные","перчатки беспалые","перчатка эластик зебра","перчатка ниточный","вязаная скатертт","archdale nitrimax перчатки нитриловые голубые","перчатки с латексным покрытием","перчатки нитрил полное покрытие крага"],"keyWords":null,"resultWithDescription":[{"probability":100,"code":"6116102000","description":"Перчатки, пропитанные или с покрытием резиной, трикотажные, машинного  или ручного вязания","startDate":"2022-01-01T00:00:00","endDate":null,"isOld":false}],"result":null,"group":{"code":"6116XXXXXX","name":"Перчатки, рукавицы и митенки трикотажные машинного или ручного вязания:"},"session":{"id":"41f850b9-2940-4157-b991-795f2e2681fb","date":"2023-07-25T13:22:46.3685935Z","remain":null},"codesCount":1,"operationTimeSpan":"00:00:00.0415551","identical":false,"responseState":201,"errorMessage":null,"success":true}