{"queryCode":{"vto":"“овар не входит в перечень изъ€тий ¬“ќ","rate":{"grName":"63 –ешение  оллегии ≈Ё  от 12.04.2022","url":"https://docs.eaeunion.org/docs/ru-ru/01532163/err_15042022_63","rateStr":"5%"},"transition":[]},"similar":["керамические шары","palomar","керамический носитель","керамический тигель","инертные шарики","нить керамическа€ lytx shandong luyang","нитеводитель"],"keyWords":null,"resultWithDescription":[{"probability":100,"code":"6909190009","description":"ѕрочие издели€ керамические дл€ лабораторных, химических или других технических целей","startDate":"2022-01-01T00:00:00","endDate":null,"isOld":false}],"result":null,"group":{"code":"6909XXXXXX","name":"»здели€ керамические дл€ лабораторных, химических или других технических целей; керамические желоба, чаны и аналогичные резервуары, используемые в сельском хоз€йстве; керамические горшки, сосуды и аналогичные издели€, используемые дл€ транспортировки или упаковки товаров:"},"session":{"id":"9b471b26-b72b-429e-8e7d-43a1b1a9f914","date":"2023-07-25T12:31:08.3652233Z","remain":null},"codesCount":1,"operationTimeSpan":"00:00:00.1224079","identical":false,"responseState":201,"errorMessage":null,"success":true}