{"queryCode":{"vto":"Товар не входит в перечень изъятий ВТО","rate":{"grName":"80 Решение Совета ЕЭК от 14.09.2021","url":"https://docs.eaeunion.org/docs/ru-ru/01530209/err_06102021_80","rateStr":"5%"},"transition":[]},"similar":[],"keyWords":null,"resultWithDescription":[{"probability":100,"code":"7208512001","description":"Прокат плоский из железа или нелегированной стали шириной 600 мм или более, горячекатаный, неплакированный, без гальванического или другого покрытия, не в рулонах, без дальнейшей обработки, кроме горячей прокатки, прочий, толщиной более 15 мм, прокатанный по четырем граням или в прямоугольном закрытом калибре, шириной не более 1250 мм ","startDate":"2022-01-01T00:00:00","endDate":null,"isOld":false}],"result":null,"group":{"code":"7208XXXXXX","name":"Прокат плоский из железа или нелегированной стали шириной 600\u00A0мм или более, горячекатаный, неплакированный, без гальванического или другого покрытия:"},"session":{"id":"23bbc1fa-996f-4a11-8a59-db07eb71c3ec","date":"2023-07-25T16:19:20.1217937Z","remain":null},"codesCount":1,"operationTimeSpan":"00:00:00.0372715","identical":false,"responseState":201,"errorMessage":null,"success":true}