{"queryCode":{"vto":"Товар не входит в перечень изъятий ВТО","rate":{"grName":"80 Решение Совета ЕЭК от 14.09.2021","url":"https://docs.eaeunion.org/docs/ru-ru/01530209/err_06102021_80","rateStr":"5%"},"transition":[]},"similar":[],"keyWords":null,"resultWithDescription":[{"probability":100,"code":"7217902000","description":"Проволока из железа или нелегированной стали, прочая, содержащая менее 0,25 мас.% углерода ","startDate":"2022-01-01T00:00:00","endDate":null,"isOld":false}],"result":null,"group":{"code":"7217XXXXXX","name":"Проволока из железа или нелегированной стали:"},"session":{"id":"ef7dcd3e-91de-4cea-b4a6-940c6fde15ae","date":"2023-07-25T14:23:21.8751564Z","remain":null},"codesCount":1,"operationTimeSpan":"00:00:00.0382042","identical":false,"responseState":201,"errorMessage":null,"success":true}