{"queryCode":{"vto":"Товар не входит в перечень изъятий ВТО","rate":{"grName":"63 Решение Коллегии ЕЭК от 12.04.2022","url":"https://docs.eaeunion.org/docs/ru-ru/01532163/err_15042022_63","rateStr":"15%"},"transition":[]},"similar":["рукоделие","шило","рукоделия","для рукоделия","крючок","спицы для вязания","крючки","вязальные спицы","вязальный крючок","вязальные крючки","товар для рукоделия","шило канцелярское большое","шило сапожное","набор спиц","крючек вязальный","иголки для вязания","аксесуар для рукоделия","игла шило металлическая","вязальная провалка","вязальные иглы","вязальная проволка китай","вязальная","иглы для рукоделия","клин вязальный","кружева ручной работы","машины вязальные","нобор для рукоделия","стальные иглы портновские","творчество рукоделие","чулочные","шило нодфиль","шило эбру металл"],"keyWords":null,"resultWithDescription":[{"probability":100,"code":"7319909000","description":"Спицы вязальные, шила, крючки вязальные, иглы деккерные и аналогичные изделия, для ручной работы, из черных металлов;  прочие","startDate":"2022-01-01T00:00:00","endDate":null,"isOld":false}],"result":null,"group":{"code":"7319XXXXXX","name":"Иглы швейные, спицы вязальные, шила, крючки вязальные, иглы деккерные и аналогичные изделия, для ручной работы, из черных металлов; английские и прочие булавки, из черных металлов, в других товарных позициях не поименованные или не включенные:"},"session":{"id":"b92f6e5b-5af8-4825-ab03-89ad1e6f62fd","date":"2023-07-25T13:15:31.2541999Z","remain":null},"codesCount":1,"operationTimeSpan":"00:00:00.0399339","identical":false,"responseState":201,"errorMessage":null,"success":true}