{"queryCode":{"vto":"Товар входит в перечень изъятий ВТО. При применении пониженной ставки является условно выпущенным и подлежит использованию только в РК. Решение Совета ЕЭК от 14.10.2015 г. № 59 в редакции Решения Совета ЕЭК от 30.10.2020 г. № 95","rate":{"grName":"80 Решение Совета ЕЭК от 14.09.2021","url":"https://docs.eaeunion.org/docs/ru-ru/01530209/err_06102021_80","rateStr":"12%"},"transition":[]},"similar":["липлент","штрипс металлический","гидроизоляционная","липлент о","инвалид","сотовая"],"keyWords":null,"resultWithDescription":[{"probability":100,"code":"7606111000","description":"Плиты, листы, полосы или ленты толщиной более 0,2 мм, прямоугольные (включая квадратные), из алюминия нелегированного, окрашенные, лакированные или покрытые пластмассой ","startDate":"2022-01-01T00:00:00","endDate":null,"isOld":false}],"result":null,"group":{"code":"7606XXXXXX","name":"Плиты, листы, полосы или ленты алюминиевые толщиной более 0,2\u00A0мм:"},"session":{"id":"57fa51a8-d0ee-47c3-81ab-0d5a50ad9405","date":"2023-07-25T14:45:51.2848228Z","remain":null},"codesCount":1,"operationTimeSpan":"00:00:00.0587709","identical":false,"responseState":201,"errorMessage":null,"success":true}