{"queryCode":{"vto":"Товар не входит в перечень изъятий ВТО","rate":{"grName":"80 Решение Совета ЕЭК от 14.09.2021","url":"https://docs.eaeunion.org/docs/ru-ru/01530209/err_06102021_80","rateStr":"3%"},"transition":[]},"similar":["ключ газовый","ключ разводной","ключ трубный","ключ трубный рычажный","ключ ктр","ключ трубный рычажный ктр","ключ цепной","ключи газовые","газовый разводной ключ","утеплитель трубный","клупп трубный сибртех","ключ раздвижной","ключ газовый рычажный ктр","ключ трубный рычажный литой","ключи трубные","ключ трубный газовый","разводные","клупп трубный","ключ газовый ктр","ктр","ключ трубный рычажный ктр лакокрас низ","ключ трубный цепной","ключ кшс","ключ газовый омедн ктр","лакокрас","ridgid","ключ трубный ржачный","ключи трубный рычажной ктр","пучок трубный ребойлера","ключ трубный рычажный ктр сибртех","ключ трубный рычажной","ключ разводной хромированный sparta","ключ переставной","газовый ключ большой","ridgid jgjhf","ключ трубный штанговый","разводной механизм","клупп трубный мечик","ключ водопроводный","ключ газовый рычажный","ключ крокодил","ключ развод универс","ключ разводной до","ключ рычажный","ключ трубный kraftool рычажный","ключ трубный на","ключ трубный рычажный ktp низ россия","ключ трубный рычажный сибртех","ключ трубчатый рычажный ктр литой","ключи сантехнические"],"keyWords":null,"resultWithDescription":[{"probability":100,"code":"8204120000","description":"Ключи гаечные ручные, разводные","startDate":"2022-01-01T00:00:00","endDate":null,"isOld":false}],"result":null,"group":{"code":"8204XXXXXX","name":"Ключи гаечные ручные (включая гаечные ключи с торсиометрами, но исключая воротки); сменные головки для гаечных ключей, с ручками или без них:"},"session":{"id":"f3344927-db8c-457d-ba96-c0d7ae8d5c7b","date":"2023-07-25T12:59:50.9888658Z","remain":null},"codesCount":1,"operationTimeSpan":"00:00:00.0395082","identical":false,"responseState":201,"errorMessage":null,"success":true}