{"queryCode":{"vto":"Товар не входит в перечень изъятий ВТО","rate":{"grName":"80 Решение Совета ЕЭК от 14.09.2021","url":"https://docs.eaeunion.org/docs/ru-ru/01530209/err_06102021_80","rateStr":"5%"},"transition":[]},"similar":["алмазная коронка","коронка","коронка по кафелю","коронки алмазные","коронка алмазная по керамограниту","сверло алмазное","алмазные сверла","алмазное бурение","сегмент коронки diamaster","сверло по керамограниту","коронка алмазного сверления проалмаз","коронка зубр биметалическая","коронка алмазная для кафеля","сегмент коронки","коронка по керамограниту","коронка для алмазного бурения","алмазное бурение каронка","трубчатое сверло железобетон premium арт","термокружки с нанесением","сверло","сверлло по кафелю","набор для сверления","коронки по гкл алмазные","коронки алмазные по кафелю стеклу","коронка по гипсокортону","коронка алмазного сверления","коронка алмазная по керамограниту fit","алмазная трубчатая коронка hammer flex dhs алмаз керамогранит","алмазная коронка по граниту","алмаз","gcb hjvtnh","алмазы"],"keyWords":null,"resultWithDescription":[{"probability":100,"code":"8207501000","description":"Инструменты для сверления, кроме инструментов для бурения скальных пород, с рабочей частью из алмаза или агломерированного алмаза","startDate":"2022-01-01T00:00:00","endDate":null,"isOld":false}],"result":null,"group":{"code":"8207XXXXXX","name":"Сменные рабочие инструменты для ручных инструментов, с механическим приводом или без него или для станков (например, для прессования, штамповки, вырубки, нарезания резьбы, сверления, растачивания, протягивания, фрезерования, токарной обработки или завинчивания), включая фильеры для волочения или экструдирования металла, инструменты для бурения скальных пород или грунтов:"},"session":{"id":"bfc031c3-5462-434c-90db-fe37dfe8b99d","date":"2023-07-25T14:01:25.4958464Z","remain":null},"codesCount":1,"operationTimeSpan":"00:00:00.0364215","identical":false,"responseState":201,"errorMessage":null,"success":true}