{"queryCode":{"vto":"Товар не входит в перечень изъятий ВТО","rate":{"grName":"80 Решение Совета ЕЭК от 14.09.2021","url":"https://docs.eaeunion.org/docs/ru-ru/01530209/err_06102021_80","rateStr":"5%"},"transition":[]},"similar":["коронка твердосплавная","быстрорез","твердосплавное монолитное сверло","кобальтовое","бесщеточная электродрель","коронка кольцевая по металлу с корбид вставками","коронка твердосплавная бородавчатая ктб","победитовые","сверло кобальтовое"],"keyWords":null,"resultWithDescription":[{"probability":100,"code":"8207507000","description":"Прочие инструменты для обработки металла, с рабочей частью из других материалов","startDate":"2022-01-01T00:00:00","endDate":null,"isOld":false}],"result":null,"group":{"code":"8207XXXXXX","name":"Сменные рабочие инструменты для ручных инструментов, с механическим приводом или без него или для станков (например, для прессования, штамповки, вырубки, нарезания резьбы, сверления, растачивания, протягивания, фрезерования, токарной обработки или завинчивания), включая фильеры для волочения или экструдирования металла, инструменты для бурения скальных пород или грунтов:"},"session":{"id":"ab15b983-9008-4df4-8060-e5ad159f9fac","date":"2023-07-25T13:57:43.9773117Z","remain":null},"codesCount":1,"operationTimeSpan":"00:00:00.0383705","identical":false,"responseState":201,"errorMessage":null,"success":true}