{"queryCode":{"vto":"Товар не входит в перечень изъятий ВТО","rate":{"grName":"76 (2022) Решение Совета ЕЭК от 15.04.2022","url":"https://docs.eaeunion.org/docs/ru-ru/01532476/err_28042022_76","rateStr":"10%"},"transition":[]},"similar":["ручка дверная","дверные ручки","защелка","дверная фурнитура","глазок дверной","шпингалет дверной","дверной ограничитель","стопор дверной","крепёж","упор дверной","щеколда","защелка дверная","ручка дверная металлическая","задвижка накладная","задвижка дверная","магнитная защелка","ручка межкомнатная","ручка балконная","пробой ушко","ручка поворотная","дверная планка","задвижка дверная цинк","защелка электромеханическая","цепочка дверная","защелка врезная","двери входные алюминевые теплой серии цвет антроцит","дверное плотно","дверной механизм","дверной тросик","защелка apecs","защелки","ручка дверная автомобильная","защелка балконной двери","замок для межкомнатных дверей","дверной цилиндр","ключи дверные","комплект ручек дверных","ручка дверная раздельная","фурнетура","дверной молоток","дверная створка","дверной гарнитур","антипаника","алюминевые уголки","защелка элекромеханическая","короб для межкомнатной двери","поворотная ручка ключей","пробой ушко цинк","ролик дверной","ручка duet дверная черный никель"],"keyWords":null,"resultWithDescription":[{"probability":100,"code":"8302411000","description":"Крепежная арматура, фурнитура и аналогичные детали прочие, для дверей","startDate":"2022-01-01T00:00:00","endDate":null,"isOld":false}],"result":null,"group":{"code":"8302XXXXXX","name":"Крепежная арматура, фурнитура и аналогичные изделия из недрагоценных металлов, используемые для мебели, дверей, лестниц, окон, штор, в салонах транспортных средств, шорных изделий, чемоданов, ящиков, шкатулок или аналогичных изделий; вешалки для шляп, крючки для шляп, кронштейны и аналогичные изделия из недрагоценных металлов; мебельные колеса с крепежными приспособлениями из недрагоценных металлов; автоматические устройства из недрагоценных металлов для закрывания дверей:"},"session":{"id":"e1f5bfc7-8b9c-4252-b488-4056427f6de9","date":"2023-07-25T16:17:01.6880866Z","remain":null},"codesCount":1,"operationTimeSpan":"00:00:00.0400736","identical":false,"responseState":201,"errorMessage":null,"success":true}