{"queryCode":{"vto":"Товар не входит в перечень изъятий ВТО","rate":{"grName":"63 Решение Коллегии ЕЭК от 12.04.2022","url":"https://docs.eaeunion.org/docs/ru-ru/01532163/err_15042022_63","rateStr":"10%"},"transition":[]},"similar":["металлорукав","труба металлическая","трубопровод","труба гофрированная","сильфон","гибкая подводка","гибкая вставка","топливопровод","труба нержавеющая aisi","труба нержавейка","компенсатор","компенсатор сильфонный","трубопровод пара","трубопроводы","маслопровод","гибкая труба","гофротруба","газовый компенсатор","трубы нержавеющие","подводка вод сталь","топливная труба","труба метал","гибкий неон","металорукав","компенсатор линзовый","сильфон ямз","гусак гибкий","грязевая труба","компенсатор давления","гибкий камень","металлическая гофра","металлорукав гофра","трубки металлические","возвратный маслопровод","гидравлическая труба","гофра с протяжкой пвх","соединение гибкое","трубы гибкие","трубка обратка","компенсаторы","подводка гибкая газа нерж","подводка для газа","реакционные трубы","труба гофра пвх с протяжкой","труба гофрированная из нержавеющей стали","труба металлический","трубка масляная металлическая","гофрированные трубы","труба гофрированная нержавеющая","труба гофрированный"],"keyWords":null,"resultWithDescription":[{"probability":100,"code":"8307100009","description":"Прочие трубы гибкие из недрагоценных металлов, с фитингами или без них, из черных металлов","startDate":"2022-01-01T00:00:00","endDate":null,"isOld":false}],"result":null,"group":{"code":"8307XXXXXX","name":"Трубы гибкие из недрагоценных металлов, с фитингами или без них:"},"session":{"id":"d68fea55-790b-4427-9a97-5fb52c5c59b3","date":"2023-07-25T12:59:07.0752165Z","remain":null},"codesCount":1,"operationTimeSpan":"00:00:00.0673620","identical":false,"responseState":201,"errorMessage":null,"success":true}