{"queryCode":{"vto":"Товар не входит в перечень изъятий ВТО","rate":{"grName":"80 Решение Совета ЕЭК от 14.09.2021","url":"https://docs.eaeunion.org/docs/ru-ru/01530209/err_06102021_80","rateStr":"7%"},"transition":[]},"similar":["весы","весы электронные","весы кухонные","весы напольные","весы безмен","весы до","весы бытовые","весы кухонные электронные","аналитические весы","весы механические","умные весы","безмен","мелкая бытовая техника","карманные весы","весы напольные электронные","термоголовка на весы","весы для ванной","весы ювелирные","весы ручные","весы настольные","весы медицинские электронные","весы электронные медецинские","весы электронные настольные","кухонный весы","весы напольные механические","ложка весы","весы на польные","весы доза с релей выход","весы технические","весы электронные бытовые","весы электронные автомобильные для статистического взвешивания","безмен электронный","весы аналитические abs analitical balance","весы для определения жира","весы механические для багажа","весы наполные","весы напольные бытовые до","весы с ростомером","весы платформенн","весы порционние","весы электронные вагонные стационарные для статистического взвешивания типа палуан вэв","мерная ложка весы","портативные весы","прочие весы","весы с печатью","весы с карточками","весы с блютузом","весы подвесные","весы под сигар","весы напольные электронные максимально допустимый вес элемент питания"],"keyWords":null,"resultWithDescription":[{"probability":100,"code":"8423101000","description":"Весы бытовые","startDate":"2022-01-01T00:00:00","endDate":null,"isOld":false}],"result":null,"group":{"code":"8423XXXXXX","name":"Оборудование для взвешивания (кроме весов чувствительностью 0,05\u00A0г или выше), включая счетные или контрольные машины, приводимые в действие силой тяжести взвешиваемого груза; разновесы для весов всех типов:"},"session":{"id":"096fba20-e9e7-4289-a38b-7517cb22eb02","date":"2023-07-25T12:31:04.9878083Z","remain":null},"codesCount":1,"operationTimeSpan":"00:00:00.0469012","identical":false,"responseState":201,"errorMessage":null,"success":true}