{"queryCode":{"vto":"Товар не входит в перечень изъятий ВТО","rate":{"grName":"80 Решение Совета ЕЭК от 14.09.2021","url":"https://docs.eaeunion.org/docs/ru-ru/01530209/err_06102021_80","rateStr":"0%"},"transition":[]},"similar":["лебедка","лебедка электрическая","лебедка театральная","лебедка автомобильная","якорная намотка","лебедки","лифтовая лебедка","шпиль","лебедка буровая","трос для лебедки","лебедка zollern","редукторная лебедка","редукторная лебедка для автокрана с гидромеханическим приводом","лебедки шахтные","лебедка каротажная","лебедка якорная","лебедка цирковая","лебёдка цепь","лебедка бетоносмесителя","лебедка для якоря","лебедка геофизическая","лебедка троссовая","лебедка трелевачная","лебедка электрическая tor каната","лебедка электрическая tor kdj","ремень для лебедки","трос лебедки","электрошкаф от лебедки","трос синтетический для лебедки","траловая лебедка","редуктор грузовой лебедки","лебедка дымовая","лебедка электрическая tor jim","лебёдка электрическая","лебедка тдт","лебедка с электродвигателем","лебедка ветрогенератор","лебедка кпу","лебедка проходческая","веревка в комплекте от электрического тельфера"],"keyWords":null,"resultWithDescription":[{"probability":100,"code":"8425310000","description":"Лебедки, кабестаны с приводом от электрического двигателя","startDate":"2022-01-01T00:00:00","endDate":null,"isOld":false}],"result":null,"group":{"code":"8425XXXXXX","name":"Тали подъемные и подъемники, кроме скиповых подъемников; лебедки и кабестаны; домкраты:"},"session":{"id":"7cb8c26f-11c4-4dcc-b15e-a55da35ef7e4","date":"2023-07-25T12:59:57.7096061Z","remain":null},"codesCount":1,"operationTimeSpan":"00:00:00.0371432","identical":false,"responseState":201,"errorMessage":null,"success":true}