{"queryCode":{"vto":"Товар не входит в перечень изъятий ВТО","rate":{"grName":"80 Решение Совета ЕЭК от 14.09.2021","url":"https://docs.eaeunion.org/docs/ru-ru/01530209/err_06102021_80","rateStr":"0%"},"transition":[]},"similar":["фальцевально","склеивающая машина","фальцевально склеивающая машина"],"keyWords":null,"resultWithDescription":[{"probability":100,"code":"8441300000","description":"Машины для изготовления картонных коробок, коробок, ящиков, труб, барабанов или аналогичных емкостей способами, отличными от формования","startDate":"2022-01-01T00:00:00","endDate":null,"isOld":false}],"result":null,"group":{"code":"8441XXXXXX","name":"Оборудование для производства изделий из бумажной массы, бумаги или картона, включая резательные машины всех типов, прочее:"},"session":{"id":"85b68705-2c3e-4bf1-b865-b4330778c0c5","date":"2023-07-25T14:45:34.4967686Z","remain":null},"codesCount":1,"operationTimeSpan":"00:00:00.0413413","identical":false,"responseState":201,"errorMessage":null,"success":true}