{"queryCode":{"vto":"Товар не входит в перечень изъятий ВТО","rate":{"grName":"80 Решение Совета ЕЭК от 14.09.2021","url":"https://docs.eaeunion.org/docs/ru-ru/01530209/err_06102021_80","rateStr":"0%"},"transition":[]},"similar":["fff","принтер","трехмерное моделирование"],"keyWords":null,"resultWithDescription":[{"probability":100,"code":"8477598000","description":"Прочие машины для литья или формования любым другим способом резины или пластмасс или для производства продукции из этих материалов, в другом месте данной группы не поименованные или не включенные","startDate":"2022-01-01T00:00:00","endDate":null,"isOld":false}],"result":null,"group":{"code":"8477XXXXXX","name":"Оборудование для обработки резины или пластмасс или для производства продукции из этих материалов, в другом месте данной группы не поименованное или не включенное:"},"session":{"id":"d60c7ed5-dae7-47ac-96b4-50fadfd6986e","date":"2023-07-25T15:02:12.5000177Z","remain":null},"codesCount":1,"operationTimeSpan":"00:00:00.0470106","identical":false,"responseState":201,"errorMessage":null,"success":true}