{"queryCode":{"vto":"Товар не входит в перечень изъятий ВТО","rate":null,"transition":[{"codeFrom":"8501320009","codeTo":"8501320008","description":"Двигатели постоянного тока прочие; генераторы постоянного тока, кроме генераторов фотоэлектрических, номинальной выходной мощностью более 750 вт, но не более 75 квт, прочие"},{"codeFrom":"8501320009","codeTo":"ex8501720000","description":"Генераторы постоянного тока фотоэлектрические, номинальной выходной мощностью более 50 вт"}]},"similar":["редутор","туннель","редутор по","мотор редутор","дезинфекционный туннель","двигатель для электросамокатов"],"keyWords":null,"resultWithDescription":[{"probability":100,"code":"8501320009","description":"ДВИГАТЕЛИ ПОСТОЯННОГО ТОКА ПРОЧИЕ; ГЕНЕРАТОРЫ ПОСТОЯННОГО ТОКА, НОМИНАЛЬНОЙ ВЫХОДНОЙ МОЩНОСТЬЮ БОЛЕЕ 750 ВТ, НО НЕ БОЛЕЕ 75 КВТ, ПРОЧИЕ     ","startDate":"2017-01-01T00:00:00","endDate":"2021-12-31T00:00:00","isOld":true}],"result":null,"group":{"code":"8501XXXXXX","name":"Двигатели и генераторы электрические (кроме электрогенераторных установок):"},"session":{"id":"b827dda1-d7e8-4f20-a13c-c72a3f565b19","date":"2023-07-25T16:20:50.7522424Z","remain":null},"codesCount":1,"operationTimeSpan":"00:00:00.0537766","identical":false,"responseState":201,"errorMessage":null,"success":true}