{"queryCode":{"vto":"Товар не входит в перечень изъятий ВТО","rate":{"grName":"66 (2022) Решение Коллегии ЕЭК от 19.04.2022","url":"https://docs.eaeunion.org/docs/ru-ru/01532480/err_28042022_66","rateStr":"10%"},"transition":[]},"similar":["шввп","кабель кпснг frls","провод термостойкий","провод рпш","провод мгтф","провод мкэш","шинка","термостойкий провод ркгм","кспв","кабель тппэп","кпснг frls пульс кабель огнестойкий для опс и соуэ однопроволочный неэкранированный","кабель рпш","кспв паритет","кпснг frls","кабель мкэшвнг","рпш","провод бпдо","шинка гребенчатая","провод стренга","зажим провода","провода с неизолированными проводниками","провод шввп гост","кпсэнг frls пульс кабель огнестойкий для опс и соуэ однопроволочный экранированный","кпсэнг frls","кабель рпш с тростиком","пвс гост ekt","пвс бухта","мкэш","кабель сварочный gkw","кабель киловат герц","гребенчатая шинка мод","шина медная гибкая","провод медный шввп сеч","провод мед ввг","пксв провод кросовый","троллейный","электропроводник","провод"],"keyWords":null,"resultWithDescription":[{"probability":100,"code":"8544499509","description":"Проводники электрические на напряжение более 80 в, но менее 1000 в, прочие ","startDate":"2022-01-01T00:00:00","endDate":null,"isOld":false}],"result":null,"group":{"code":"8544XXXXXX","name":"Провода изолированные (включая эмалированные или анодированные), кабели (включая коаксиальные кабели) и другие изолированные электрические проводники с соединительными приспособлениями или без них; кабели волоконно-оптические, составленные из волокон с индивидуальными оболочками, независимо от того, находятся они или нет в сборе с электропроводниками или соединительными приспособлениями:"},"session":{"id":"63b812ea-9e7f-42e0-a110-6bca72e676d0","date":"2023-07-25T12:59:47.5716767Z","remain":null},"codesCount":1,"operationTimeSpan":"00:00:00.0994945","identical":false,"responseState":201,"errorMessage":null,"success":true}