{"queryCode":{"vto":"Товар не входит в перечень изъятий ВТО","rate":{"grName":"80 Решение Совета ЕЭК от 14.09.2021","url":"https://docs.eaeunion.org/docs/ru-ru/01530209/err_06102021_80","rateStr":"5%"},"transition":[]},"similar":["коробка","коробка отбора мощности","коробка раздаточная","раздатка","архивная коробка","коробка для ланча","механическая коробка передач","коробка под автомат","коробка протяжная","nhe","коробка раздаточная камаз","переферия","автоматическая коробка передач","ksc коробка о у","коробка отбора","коробка передач ступенчатая нового образца","коробка пласт","коробка раздаточная краз","механическая коробка переключения передач","коробка кртм в","рапределительная коробка","коробка ksc","коробка кртм в шпд плинт","ksc коробка распаячн о","гидрофильтр автоматическая коробка передач","коробка раздаточная газ","коробка распределения","коробка у","труба","nhe vtlyfz","автоматическая оснаска для штампа","девятиступенчатая механическая коробка передач","коробка деревяная","коробка для стерили","коробка кртм","коробка отвентительная","коробка подаро","коробка рахдаточная","коробка стерили","развет коробка","трубкапластинка поляриметрическая","свадебная коробка","коробка переменых передач механическая","коробка переключения передачь","коробка передач скоробкой раздаточнойв сборе","коробка отбора мощностиkаmаz","коробка о у","коробка на автомат","коробка крафтовая","коробка кмр"],"keyWords":null,"resultWithDescription":[{"probability":100,"code":"8708405009","description":"Коробки передач, прочие ","startDate":"2022-01-01T00:00:00","endDate":null,"isOld":false}],"result":null,"group":{"code":"8708XXXXXX","name":"Части и принадлежности моторных транспортных средств товарных позиций 8701\u00A0–\u00A08705:"},"session":{"id":"57332e58-8fa7-461b-9609-69f30712350e","date":"2023-07-25T16:18:42.9926653Z","remain":null},"codesCount":1,"operationTimeSpan":"00:00:00.0570395","identical":false,"responseState":201,"errorMessage":null,"success":true}