{"queryCode":{"vto":"Товар входит в перечень изъятий ВТО. При применении пониженной ставки является условно выпущенным и подлежит использованию только в РК. Решение Совета ЕЭК от 14.10.2015 г. № 59 в редакции Решения Совета ЕЭК от 30.10.2020 г. № 95","rate":{"grName":"80 Решение Совета ЕЭК от 14.09.2021","url":"https://docs.eaeunion.org/docs/ru-ru/01530209/err_06102021_80","rateStr":"10%"},"transition":[]},"similar":["детские игрушки","деревянные игрушки","набор","набор для творчества","деревянная игрушка","набор для рисования","детская игрушка","набор посуды","набор для шитья","набор для рукоделия","домик для животных","игрушка для кошек","наборы для творчества","присыпка детская","кухонный набор","игровой набор","игровой коврик","кукольный домик","набор настольный","корзина для игрушек","детские коврики","кукла ручной работы","игрушки из дерева","игровые наборы","одежда игрушка","тефаль","игрушка ручной работы","набор для пикника","наборы","игрушка из шерсти","детская площадка","дорожный набор","игрушка из пластмассы","бутылочка детская","набор для вышивки","швейный набор","для творчества","кукольный дом","детская горка","пенный генератор игрушка","набор для ванны","игрушки для кошек","мебель для кукол","игровой автомат","набор художника","наборы для пасхи","наборы для рисования","силиконовые игрушки","игрушка из фетра","набор для ванной"],"keyWords":null,"resultWithDescription":[{"probability":100,"code":"9503007000","description":" игрушки в наборах или комплектах прочие ","startDate":"2022-01-01T00:00:00","endDate":null,"isOld":false}],"result":null,"group":{"code":"950300XXXX","name":"Трехколесные велосипеды, самокаты, педальные автомобили и аналогичные игрушки на колесах; коляски для кукол; куклы; прочие игрушки; модели в уменьшенном размере (\"в масштабе\") и аналогичные модели для развлечений, действующие или недействующие; головоломки всех видов:"},"session":{"id":"2ee15487-63f4-4605-8be9-2d0d447e3bb1","date":"2023-07-25T12:06:09.2244288Z","remain":null},"codesCount":1,"operationTimeSpan":"00:00:00.0704229","identical":false,"responseState":201,"errorMessage":null,"success":true}