{"queryCode":{"vto":"Товар входит в перечень изъятий ВТО. При применении пониженной ставки является условно выпущенным и подлежит использованию только в РК. Решение Совета ЕЭК от 14.10.2015 г. № 59 в редакции Решения Совета ЕЭК от 30.10.2020 г. № 95","rate":{"grName":"80 Решение Совета ЕЭК от 14.09.2021","url":"https://docs.eaeunion.org/docs/ru-ru/01530209/err_06102021_80","rateStr":"15%"},"transition":[]},"similar":["сито","сито нерж","сито полиамидное для лаборатории","сита","решето","сито металлическое","сито лабораторное","стрейнер","кружка сито","сито кухонное","сито для чая","reko барабанное сито","вибрационное сито","решет","сито для раковины","сито полеуретановая","сито бумаж","сито для чайника","сито с ручкой","сито с перфорированным полотном","малекулярное сито","сито барное","сито лаб","сито домашнее","сито для сахарной пудры","сито для лаборатории","сито для камнеотделитель","сито в раковину","сито барабанное полигональное","сита шпальтовые","решета","противоразбрызгиватель","нержавеющее сито","металотканые сита","металотканое сито","металлическая сита","сито дуршлаг","мелекулярное сито","топервар сито","сито чайное","сито среднее","сито с перферацией","сито пробивное","сито нержавееющее","сито мкталлическое","сито металл","сито метал","железное сито","дуршлаг алюминь","для просеивания"],"keyWords":null,"resultWithDescription":[{"probability":100,"code":"9604000000","description":"Сита и решета ручные","startDate":"2022-01-01T00:00:00","endDate":null,"isOld":false}],"result":null,"group":{"code":"9604000000","name":"Сита и решета ручные"},"session":{"id":"6e18d81f-7125-4736-a132-3e3577f558ca","date":"2023-07-25T16:11:46.3397087Z","remain":null},"codesCount":1,"operationTimeSpan":"00:00:00.0465177","identical":false,"responseState":201,"errorMessage":null,"success":true}