{"queryCode":{"vto":"“овар не входит в перечень изъ€тий ¬“ќ","rate":{"grName":"80 –ешение —овета ≈Ё  от 14.09.2021","url":"https://docs.eaeunion.org/docs/ru-ru/01530209/err_06102021_80","rateStr":"10%"},"transition":[]},"similar":["расческа","заколка дл€ волос","расчески","расческа дл€ волос","расчЄска","расчески дл€ волос","расчЄска дл€ волос","свадебный гребень","расчЄски","расческа пластикова€","массажна€","hair clip","массажна€ расческа детска€","массажна€ расческа","расческ","пуходерки","расческа складна€","расческа грумминг","набор дл€ волос щетка расческа","щетка ножницы расческа","очиститель расчесок","расческа cure","волосы конский хвост","массажн","лазерные расчески","ножницы расческа","расческа гребень","щетка расческа дл€ детей","щетка расческа","рачески","расчески гребни","туалетна€ расческа","расчестки","гребень украшение","детска€ щетка и расческа","гребень бабочки","farres расчЄска брашинг цветна€","canpol расческа с гребешком овальна€","расчестка скелетна€","расчески и заколки","расческа строительна€","расческа из пластика","расческа жатки","расчЄска дл€ новорождЄнных","расческа брашинг","очиститель дл€ расчесок","антистат"],"keyWords":null,"resultWithDescription":[{"probability":100,"code":"9615110000","description":"–асчески, гребни дл€ волос и аналогичные предметы из твердой резины или пластмасс","startDate":"2022-01-01T00:00:00","endDate":null,"isOld":false}],"result":null,"group":{"code":"9615XXXXXX","name":"–асчески, гребни дл€ волос и аналогичные предметы; шпильки дл€ волос, зажимы дл€ завивки, бигуди и аналогичные предметы, кроме указанных в товарной позиции 8516, и их части:"},"session":{"id":"6fa35b73-ac20-4f86-9d11-a8638b9a1cd4","date":"2023-07-25T15:21:38.477409Z","remain":null},"codesCount":1,"operationTimeSpan":"00:00:00.0596075","identical":false,"responseState":201,"errorMessage":null,"success":true}